m6/__init__.py
m6/conventions.py
m6/nothin.py
m6/bruteforce/__init__.py
m6/bruteforce/freelunchportfolio.py
m6/bruteforce/scenarioexamples.py
m6/bruteforce/sceneriogeneration.py
m6/bruteforce/shgoportfolio.py
m6-0.0.3.dist-info/LICENSE
m6-0.0.3.dist-info/METADATA
m6-0.0.3.dist-info/WHEEL
m6-0.0.3.dist-info/entry_points.txt
m6-0.0.3.dist-info/top_level.txt
m6-0.0.3.dist-info/RECORD
