Metadata-Version: 2.1
Name: m6
Version: 0.0.3
Summary: Utilities for M6 Financial Forecasting Competition
Home-page: https://github.com/microprediction/m6
Author: microprediction
Author-email: peter.cotton@microprediction.com
License: MIT
Platform: UNKNOWN
Classifier: License :: OSI Approved :: MIT License
Classifier: Programming Language :: Python :: 3
Classifier: Programming Language :: Python :: 3.7
Classifier: Programming Language :: Python :: 3.8
License-File: LICENSE
Requires-Dist: wheel
Requires-Dist: pathlib
Requires-Dist: numpy
Requires-Dist: scikit-learn
Requires-Dist: runthis
Requires-Dist: freelunch
